{
  "type": "Feature",
  "stac_version": "1.1.0",
  "stac_extensions": [
    "https://stac-extensions.github.io/ssys/v1.1.0/schema.json"
  ],
  "id": "20180421_183121_1p0a_LNO_1_DF_119_00533_242",
  "geometry": {
    "type": "Polygon",
    "coordinates": [
      [
        [
          -150.3831,
          -73.1923
        ],
        [
          -150.3703,
          -73.1859
        ],
        [
          -151.1672,
          -73.0506
        ],
        [
          -151.473,
          -73.0286
        ],
        [
          -151.4861,
          -73.035
        ],
        [
          -150.6916,
          -73.1711
        ],
        [
          -150.3831,
          -73.1923
        ]
      ]
    ]
  },
  "bbox": [
    -151.4861,
    -73.1923,
    -150.3703,
    -73.0286
  ],
  "properties": {
    "incidence_angle": 89.622,
    "emergence_angle": 0.556,
    "phase_angle": 89.546,
    "centre_latitude": -73.122,
    "centre_longitude": -150.851,
    "channel_temperature": -11.202,
    "start_datetime": "2018-04-21T19:42:08.163000Z",
    "end_datetime": "2018-04-21T19:42:09.986000Z",
    "platform": "exomars-trace-gas-orbiter",
    "instruments": [
      "NOMAD"
    ],
    "constellation": "exomars",
    "ssys:local_time": "34:163.102956:16.243",
    "ssys:targets": [
      "mars"
    ],
    "ssys:target_class": "planet",
    "mission": "ExoMars",
    "datetime": "2018-04-21T19:42:08.163000Z"
  },
  "links": [
    {
      "rel": "root",
      "href": "../../../catalog.json",
      "type": "application/json"
    },
    {
      "rel": "collection",
      "href": "../collection.json",
      "type": "application/json"
    },
    {
      "rel": "parent",
      "href": "../collection.json",
      "type": "application/json"
    }
  ],
  "assets": {
    "dataformat": {
      "href": "20180421_183121_1p0a_LNO_1_DF_119",
      "type": "application/x-hdf5"
    }
  },
  "collection": "diffraction-order-119"
}
