{
  "type": "Feature",
  "stac_version": "1.1.0",
  "stac_extensions": [
    "https://stac-extensions.github.io/ssys/v1.1.0/schema.json"
  ],
  "id": "20180429_132004_1p0a_LNO_1_DF_121_00533_91",
  "geometry": {
    "type": "Polygon",
    "coordinates": [
      [
        [
          -88.7107,
          -10.6177
        ],
        [
          -88.4582,
          -10.5147
        ],
        [
          -88.4777,
          -10.4258
        ],
        [
          -88.4806,
          -10.4189
        ],
        [
          -88.7333,
          -10.5214
        ],
        [
          -88.7136,
          -10.6108
        ],
        [
          -88.7107,
          -10.6177
        ]
      ]
    ]
  },
  "bbox": [
    -88.7333,
    -10.6177,
    -88.4582,
    -10.4189
  ],
  "properties": {
    "incidence_angle": 38.549,
    "emergence_angle": 0.534,
    "phase_angle": 39.033,
    "centre_latitude": -10.532,
    "centre_longitude": -88.612,
    "channel_temperature": -4.732,
    "start_datetime": "2018-04-29T13:53:16.119000Z",
    "end_datetime": "2018-04-29T13:53:17.942000Z",
    "platform": "exomars-trace-gas-orbiter",
    "instruments": [
      "NOMAD"
    ],
    "constellation": "exomars",
    "ssys:local_time": "34:167.276704:9.618",
    "ssys:targets": [
      "mars"
    ],
    "ssys:target_class": "planet",
    "mission": "ExoMars",
    "datetime": "2018-04-29T13:53:16.119000Z"
  },
  "links": [
    {
      "rel": "root",
      "href": "../../../catalog.json",
      "type": "application/json"
    },
    {
      "rel": "collection",
      "href": "../collection.json",
      "type": "application/json"
    },
    {
      "rel": "parent",
      "href": "../collection.json",
      "type": "application/json"
    }
  ],
  "assets": {
    "dataformat": {
      "href": "20180429_132004_1p0a_LNO_1_DF_121",
      "type": "application/x-hdf5"
    }
  },
  "collection": "diffraction-order-121"
}
