{
  "type": "Feature",
  "stac_version": "1.1.0",
  "stac_extensions": [
    "https://stac-extensions.github.io/ssys/v1.1.0/schema.json"
  ],
  "id": "20180427_120256_1p0a_LNO_1_DP_167_00533_68",
  "geometry": {
    "type": "Polygon",
    "coordinates": [
      [
        [
          -97.5118,
          38.9053
        ],
        [
          -97.5164,
          38.8981
        ],
        [
          -97.4342,
          38.6985
        ],
        [
          -97.1011,
          38.5677
        ],
        [
          -97.0964,
          38.5749
        ],
        [
          -97.1778,
          38.7743
        ],
        [
          -97.5118,
          38.9053
        ]
      ]
    ]
  },
  "bbox": [
    -97.5164,
    38.5677,
    -97.0964,
    38.9053
  ],
  "properties": {
    "incidence_angle": 52.492,
    "emergence_angle": 0.547,
    "phase_angle": 52.633,
    "centre_latitude": 38.761,
    "centre_longitude": -97.336,
    "channel_temperature": -7.892,
    "start_datetime": "2018-04-27T12:30:05.906000Z",
    "end_datetime": "2018-04-27T12:30:10.145000Z",
    "platform": "exomars-trace-gas-orbiter",
    "instruments": [
      "NOMAD"
    ],
    "constellation": "exomars",
    "ssys:local_time": "34:166.16413:8.969",
    "ssys:targets": [
      "mars"
    ],
    "ssys:target_class": "planet",
    "mission": "ExoMars",
    "datetime": "2018-04-27T12:30:05.906000Z"
  },
  "links": [
    {
      "rel": "root",
      "href": "../../../catalog.json",
      "type": "application/json"
    },
    {
      "rel": "collection",
      "href": "../collection.json",
      "type": "application/json"
    },
    {
      "rel": "parent",
      "href": "../collection.json",
      "type": "application/json"
    }
  ],
  "assets": {
    "dataformat": {
      "href": "20180427_120256_1p0a_LNO_1_DP_167",
      "type": "application/x-hdf5"
    }
  },
  "collection": "diffraction-order-167"
}
