{
  "type": "Feature",
  "stac_version": "1.1.0",
  "stac_extensions": [
    "https://stac-extensions.github.io/ssys/v1.1.0/schema.json"
  ],
  "id": "20180429_225934_1p0a_LNO_1_DF_121_00533_198",
  "geometry": {
    "type": "Polygon",
    "coordinates": [
      [
        [
          148.1119,
          -58.7023
        ],
        [
          148.2243,
          -58.4414
        ],
        [
          148.0167,
          -58.2578
        ],
        [
          148.0029,
          -58.2562
        ],
        [
          147.8887,
          -58.5168
        ],
        [
          148.0979,
          -58.7007
        ],
        [
          148.1119,
          -58.7023
        ]
      ]
    ]
  },
  "bbox": [
    147.8887,
    -58.7023,
    148.2243,
    -58.2562
  ],
  "properties": {
    "incidence_angle": 64.831,
    "emergence_angle": 0.436,
    "phase_angle": 64.521,
    "centre_latitude": -58.511,
    "centre_longitude": 148.065,
    "channel_temperature": -3.345,
    "start_datetime": "2018-04-29T23:59:18.688000Z",
    "end_datetime": "2018-04-29T23:59:22.927000Z",
    "platform": "exomars-trace-gas-orbiter",
    "instruments": [
      "NOMAD"
    ],
    "constellation": "exomars",
    "ssys:local_time": "34:167.504753:11.227",
    "ssys:targets": [
      "mars"
    ],
    "ssys:target_class": "planet",
    "mission": "ExoMars",
    "datetime": "2018-04-29T23:59:18.688000Z"
  },
  "links": [
    {
      "rel": "root",
      "href": "../../../catalog.json",
      "type": "application/json"
    },
    {
      "rel": "collection",
      "href": "../collection.json",
      "type": "application/json"
    },
    {
      "rel": "parent",
      "href": "../collection.json",
      "type": "application/json"
    }
  ],
  "assets": {
    "dataformat": {
      "href": "20180429_225934_1p0a_LNO_1_DF_121",
      "type": "application/x-hdf5"
    }
  },
  "collection": "diffraction-order-121"
}
