{
  "type": "Feature",
  "stac_version": "1.1.0",
  "stac_extensions": [
    "https://stac-extensions.github.io/ssys/v1.1.0/schema.json"
  ],
  "id": "20180422_122214_1p0a_LNO_1_DP_168_00533_7",
  "geometry": {
    "type": "Polygon",
    "coordinates": [
      [
        [
          -144.4887,
          58.6198
        ],
        [
          -144.4986,
          58.6131
        ],
        [
          -144.35,
          58.4817
        ],
        [
          -143.8936,
          58.2959
        ],
        [
          -143.8837,
          58.3025
        ],
        [
          -144.0304,
          58.4339
        ],
        [
          -144.4887,
          58.6198
        ]
      ]
    ]
  },
  "bbox": [
    -144.4986,
    58.2959,
    -143.8837,
    58.6198
  ],
  "properties": {
    "incidence_angle": 61.564,
    "emergence_angle": 0.639,
    "phase_angle": 61.321,
    "centre_latitude": 58.481,
    "centre_longitude": -144.233,
    "channel_temperature": -7.205,
    "start_datetime": "2018-04-22T12:34:08.894000Z",
    "end_datetime": "2018-04-22T12:34:11.995000Z",
    "platform": "exomars-trace-gas-orbiter",
    "instruments": [
      "NOMAD"
    ],
    "constellation": "exomars",
    "ssys:local_time": "34:163.478756:9.109",
    "mission": "ExoMars",
    "datetime": "2018-04-22T12:34:08.894000Z"
  },
  "links": [
    {
      "rel": "root",
      "href": "../../../catalog.json",
      "type": "application/json"
    },
    {
      "rel": "collection",
      "href": "../collection.json",
      "type": "application/json"
    },
    {
      "rel": "parent",
      "href": "../collection.json",
      "type": "application/json"
    }
  ],
  "assets": {
    "dataformat": {
      "href": "20180422_122214_1p0a_LNO_1_DP_168",
      "type": "application/x-hdf5"
    }
  },
  "collection": "diffraction-order-168"
}
