{
  "type": "Feature",
  "stac_version": "1.1.0",
  "stac_extensions": [
    "https://stac-extensions.github.io/ssys/v1.1.0/schema.json"
  ],
  "id": "20180425_070008_1p0a_LNO_1_DF_127_00533_178",
  "geometry": {
    "type": "Polygon",
    "coordinates": [
      [
        [
          -14.7636,
          -39.0839
        ],
        [
          -14.6002,
          -38.8473
        ],
        [
          -14.6839,
          -38.6448
        ],
        [
          -14.6923,
          -38.6412
        ],
        [
          -14.8568,
          -38.8771
        ],
        [
          -14.7721,
          -39.0803
        ],
        [
          -14.7636,
          -39.0839
        ]
      ]
    ]
  },
  "bbox": [
    -14.8568,
    -39.0839,
    -14.6002,
    -38.6412
  ],
  "properties": {
    "incidence_angle": 46.273,
    "emergence_angle": 0.241,
    "phase_angle": 46.408,
    "centre_latitude": -38.894,
    "centre_longitude": -14.733,
    "channel_temperature": -4.54,
    "start_datetime": "2018-04-25T07:54:57.481000Z",
    "end_datetime": "2018-04-25T07:55:01.721000Z",
    "platform": "exomars-trace-gas-orbiter",
    "instruments": [
      "NOMAD"
    ],
    "constellation": "exomars",
    "ssys:local_time": "34:164.983832:11.291",
    "mission": "ExoMars",
    "datetime": "2018-04-25T07:54:57.481000Z"
  },
  "links": [
    {
      "rel": "root",
      "href": "../../../catalog.json",
      "type": "application/json"
    },
    {
      "rel": "collection",
      "href": "../collection.json",
      "type": "application/json"
    },
    {
      "rel": "parent",
      "href": "../collection.json",
      "type": "application/json"
    }
  ],
  "assets": {
    "dataformat": {
      "href": "20180425_070008_1p0a_LNO_1_DF_127",
      "type": "application/x-hdf5"
    }
  },
  "collection": "diffraction-order-127"
}
