{
  "type": "Feature",
  "stac_version": "1.1.0",
  "stac_extensions": [
    "https://stac-extensions.github.io/ssys/v1.1.0/schema.json"
  ],
  "id": "20180424_113122_1p0a_LNO_1_DF_134_00533_158",
  "geometry": {
    "type": "Polygon",
    "coordinates": [
      [
        [
          -78.173,
          -51.9568
        ],
        [
          -78.1355,
          -51.691
        ],
        [
          -78.1965,
          -51.6075
        ],
        [
          -78.2084,
          -51.6068
        ],
        [
          -78.2471,
          -51.8726
        ],
        [
          -78.185,
          -51.9562
        ],
        [
          -78.173,
          -51.9568
        ]
      ]
    ]
  },
  "bbox": [
    -78.2471,
    -51.9568,
    -78.1355,
    -51.6068
  ],
  "properties": {
    "incidence_angle": 59.28,
    "emergence_angle": 2.137,
    "phase_angle": 58.398,
    "centre_latitude": -51.807,
    "centre_longitude": -78.188,
    "channel_temperature": -3.826,
    "start_datetime": "2018-04-24T12:21:04.288000Z",
    "end_datetime": "2018-04-24T12:21:06.111000Z",
    "platform": "exomars-trace-gas-orbiter",
    "instruments": [
      "NOMAD"
    ],
    "constellation": "exomars",
    "ssys:local_time": "34:164.545833:12.017",
    "mission": "ExoMars",
    "datetime": "2018-04-24T12:21:04.288000Z"
  },
  "links": [
    {
      "rel": "root",
      "href": "../../../catalog.json",
      "type": "application/json"
    },
    {
      "rel": "collection",
      "href": "../collection.json",
      "type": "application/json"
    },
    {
      "rel": "parent",
      "href": "../collection.json",
      "type": "application/json"
    }
  ],
  "assets": {
    "dataformat": {
      "href": "20180424_113122_1p0a_LNO_1_DF_134",
      "type": "application/x-hdf5"
    }
  },
  "collection": "diffraction-order-134"
}
