{
  "type": "Feature",
  "stac_version": "1.1.0",
  "stac_extensions": [
    "https://stac-extensions.github.io/ssys/v1.1.0/schema.json"
  ],
  "id": "20180421_203916_1p0a_LNO_1_DP_189_00533_112",
  "geometry": {
    "type": "Polygon",
    "coordinates": [
      [
        [
          114.3192,
          -16.3238
        ],
        [
          114.5287,
          -16.1446
        ],
        [
          114.5078,
          -16.0557
        ],
        [
          114.5026,
          -16.0501
        ],
        [
          114.2929,
          -16.2288
        ],
        [
          114.3141,
          -16.3182
        ],
        [
          114.3192,
          -16.3238
        ]
      ]
    ]
  },
  "bbox": [
    114.2929,
    -16.3238,
    114.5287,
    -16.0501
  ],
  "properties": {
    "incidence_angle": 24.81,
    "emergence_angle": 0.094,
    "phase_angle": 24.767,
    "centre_latitude": -16.206,
    "centre_longitude": 114.398,
    "channel_temperature": -9.275,
    "start_datetime": "2018-04-21T21:17:35.594000Z",
    "end_datetime": "2018-04-21T21:17:37.417000Z",
    "platform": "exomars-trace-gas-orbiter",
    "instruments": [
      "NOMAD"
    ],
    "constellation": "exomars",
    "ssys:local_time": "34:163.138383:11.481",
    "mission": "ExoMars",
    "datetime": "2018-04-21T21:17:35.594000Z"
  },
  "links": [
    {
      "rel": "root",
      "href": "../../../catalog.json",
      "type": "application/json"
    },
    {
      "rel": "collection",
      "href": "../collection.json",
      "type": "application/json"
    },
    {
      "rel": "parent",
      "href": "../collection.json",
      "type": "application/json"
    }
  ],
  "assets": {
    "dataformat": {
      "href": "20180421_203916_1p0a_LNO_1_DP_189",
      "type": "application/x-hdf5"
    }
  },
  "collection": "diffraction-order-189"
}
