{
  "type": "Feature",
  "stac_version": "1.1.0",
  "stac_extensions": [
    "https://stac-extensions.github.io/ssys/v1.1.0/schema.json"
  ],
  "id": "20180430_223416_1p0a_LNO_1_DF_124_00533_45",
  "geometry": {
    "type": "Polygon",
    "coordinates": [
      [
        [
          121.295,
          49.2701
        ],
        [
          121.2989,
          49.2781
        ],
        [
          121.1744,
          49.4705
        ],
        [
          120.7324,
          49.5595
        ],
        [
          120.7286,
          49.5515
        ],
        [
          120.8551,
          49.3594
        ],
        [
          121.295,
          49.2701
        ]
      ]
    ]
  },
  "bbox": [
    120.7286,
    49.2701,
    121.2989,
    49.5595
  ],
  "properties": {
    "incidence_angle": 69.417,
    "emergence_angle": 0.528,
    "phase_angle": 69.306,
    "centre_latitude": 49.394,
    "centre_longitude": 121.054,
    "channel_temperature": -4.7,
    "start_datetime": "2018-04-30T22:55:50.540000Z",
    "end_datetime": "2018-04-30T22:55:54.779000Z",
    "platform": "exomars-trace-gas-orbiter",
    "instruments": [
      "NOMAD"
    ],
    "constellation": "exomars",
    "ssys:local_time": "34:168.023332:7.754",
    "ssys:targets": [
      "mars"
    ],
    "ssys:target_class": "planet",
    "mission": "ExoMars",
    "datetime": "2018-04-30T22:55:50.540000Z"
  },
  "links": [
    {
      "rel": "root",
      "href": "../../../catalog.json",
      "type": "application/json"
    },
    {
      "rel": "collection",
      "href": "../collection.json",
      "type": "application/json"
    },
    {
      "rel": "parent",
      "href": "../collection.json",
      "type": "application/json"
    }
  ],
  "assets": {
    "dataformat": {
      "href": "20180430_223416_1p0a_LNO_1_DF_124",
      "type": "application/x-hdf5"
    }
  },
  "collection": "diffraction-order-124"
}
