{
  "type": "Feature",
  "stac_version": "1.1.0",
  "stac_extensions": [
    "https://stac-extensions.github.io/ssys/v1.1.0/schema.json"
  ],
  "id": "20180427_180633_1p0a_LNO_1_DF_127_00533_158",
  "geometry": {
    "type": "Polygon",
    "coordinates": [
      [
        [
          -152.7623,
          -56.0526
        ],
        [
          -152.6977,
          -55.7866
        ],
        [
          -152.8752,
          -55.5983
        ],
        [
          -152.8883,
          -55.5973
        ],
        [
          -152.9546,
          -55.8631
        ],
        [
          -152.7755,
          -56.0516
        ],
        [
          -152.7623,
          -56.0526
        ]
      ]
    ]
  },
  "bbox": [
    -152.9546,
    -56.0526,
    -152.6977,
    -55.5973
  ],
  "properties": {
    "incidence_angle": 62.179,
    "emergence_angle": 0.4,
    "phase_angle": 61.94,
    "centre_latitude": -55.857,
    "centre_longitude": -152.817,
    "channel_temperature": -3.053,
    "start_datetime": "2018-04-27T18:56:22.492000Z",
    "end_datetime": "2018-04-27T18:56:26.732000Z",
    "platform": "exomars-trace-gas-orbiter",
    "instruments": [
      "NOMAD"
    ],
    "constellation": "exomars",
    "ssys:local_time": "34:166.30894:11.534",
    "mission": "ExoMars",
    "datetime": "2018-04-27T18:56:22.492000Z"
  },
  "links": [
    {
      "rel": "root",
      "href": "../../../catalog.json",
      "type": "application/json"
    },
    {
      "rel": "collection",
      "href": "../collection.json",
      "type": "application/json"
    },
    {
      "rel": "parent",
      "href": "../collection.json",
      "type": "application/json"
    }
  ],
  "assets": {
    "dataformat": {
      "href": "20180427_180633_1p0a_LNO_1_DF_127",
      "type": "application/x-hdf5"
    }
  },
  "collection": "diffraction-order-127"
}
