{
  "type": "Feature",
  "stac_version": "1.1.0",
  "stac_extensions": [
    "https://stac-extensions.github.io/ssys/v1.1.0/schema.json"
  ],
  "id": "20180424_072536_1p0a_LNO_1_DF_196_00533_5",
  "geometry": {
    "type": "Polygon",
    "coordinates": [
      [
        [
          -119.1954,
          74.3745
        ],
        [
          -120.355,
          74.2512
        ],
        [
          -120.3428,
          74.243
        ],
        [
          -120.0517,
          74.2386
        ],
        [
          -118.892,
          74.36
        ],
        [
          -118.9037,
          74.3684
        ],
        [
          -119.1954,
          74.3745
        ]
      ]
    ]
  },
  "bbox": [
    -120.355,
    74.2386,
    -118.892,
    74.3745
  ],
  "properties": {
    "incidence_angle": 88.838,
    "emergence_angle": 17.259,
    "phase_angle": 106.094,
    "centre_latitude": 74.316,
    "centre_longitude": -119.562,
    "channel_temperature": -5.94,
    "start_datetime": "2018-04-24T07:37:12.919000Z",
    "end_datetime": "2018-04-24T07:37:14.741000Z",
    "platform": "exomars-trace-gas-orbiter",
    "instruments": [
      "NOMAD"
    ],
    "constellation": "exomars",
    "ssys:local_time": "34:164.440016:4.649",
    "mission": "ExoMars",
    "datetime": "2018-04-24T07:37:12.919000Z"
  },
  "links": [
    {
      "rel": "root",
      "href": "../../../catalog.json",
      "type": "application/json"
    },
    {
      "rel": "collection",
      "href": "../collection.json",
      "type": "application/json"
    },
    {
      "rel": "parent",
      "href": "../collection.json",
      "type": "application/json"
    }
  ],
  "assets": {
    "dataformat": {
      "href": "20180424_072536_1p0a_LNO_1_DF_196",
      "type": "application/x-hdf5"
    }
  },
  "collection": "diffraction-order-196"
}
