{
  "type": "Feature",
  "stac_version": "1.1.0",
  "stac_extensions": [
    "https://stac-extensions.github.io/ssys/v1.1.0/schema.json"
  ],
  "id": "20180421_203916_1p0a_LNO_1_DP_167_00533_116",
  "geometry": {
    "type": "Polygon",
    "coordinates": [
      [
        [
          114.9168,
          -18.7925
        ],
        [
          115.1174,
          -18.6022
        ],
        [
          115.0957,
          -18.5133
        ],
        [
          115.0902,
          -18.508
        ],
        [
          114.8891,
          -18.698
        ],
        [
          114.9112,
          -18.7873
        ],
        [
          114.9168,
          -18.7925
        ]
      ]
    ]
  },
  "bbox": [
    114.8891,
    -18.7925,
    115.1174,
    -18.508
  ],
  "properties": {
    "incidence_angle": 26.884,
    "emergence_angle": 0.514,
    "phase_angle": 26.894,
    "centre_latitude": -18.671,
    "centre_longitude": 114.991,
    "channel_temperature": -9.222,
    "start_datetime": "2018-04-21T21:18:25.975000Z",
    "end_datetime": "2018-04-21T21:18:27.798000Z",
    "platform": "exomars-trace-gas-orbiter",
    "instruments": [
      "NOMAD"
    ],
    "constellation": "exomars",
    "ssys:local_time": "34:163.138695:11.534",
    "mission": "ExoMars",
    "datetime": "2018-04-21T21:18:25.975000Z"
  },
  "links": [
    {
      "rel": "root",
      "href": "../../../catalog.json",
      "type": "application/json"
    },
    {
      "rel": "collection",
      "href": "../collection.json",
      "type": "application/json"
    },
    {
      "rel": "parent",
      "href": "../collection.json",
      "type": "application/json"
    }
  ],
  "assets": {
    "dataformat": {
      "href": "20180421_203916_1p0a_LNO_1_DP_167",
      "type": "application/x-hdf5"
    }
  },
  "collection": "diffraction-order-167"
}
