{
  "type": "Feature",
  "stac_version": "1.1.0",
  "stac_extensions": [
    "https://stac-extensions.github.io/ssys/v1.1.0/schema.json"
  ],
  "id": "20180426_201954_1p0a_LNO_1_DP_190_00533_32",
  "geometry": {
    "type": "Polygon",
    "coordinates": [
      [
        [
          115.1527,
          62.918
        ],
        [
          115.1591,
          62.9259
        ],
        [
          115.0417,
          62.9978
        ],
        [
          114.4086,
          63.1016
        ],
        [
          114.4023,
          63.0936
        ],
        [
          114.5217,
          63.0223
        ],
        [
          115.1527,
          62.918
        ]
      ]
    ]
  },
  "bbox": [
    114.4023,
    62.918,
    115.1591,
    63.1016
  ],
  "properties": {
    "incidence_angle": 73.79,
    "emergence_angle": 0.712,
    "phase_angle": 73.589,
    "centre_latitude": 62.997,
    "centre_longitude": 114.834,
    "channel_temperature": -5.314,
    "start_datetime": "2018-04-26T20:38:13.519000Z",
    "end_datetime": "2018-04-26T20:38:15.342000Z",
    "platform": "exomars-trace-gas-orbiter",
    "instruments": [
      "NOMAD"
    ],
    "constellation": "exomars",
    "ssys:local_time": "34:165.807565:7.667",
    "mission": "ExoMars",
    "datetime": "2018-04-26T20:38:13.519000Z"
  },
  "links": [
    {
      "rel": "root",
      "href": "../../../catalog.json",
      "type": "application/json"
    },
    {
      "rel": "collection",
      "href": "../collection.json",
      "type": "application/json"
    },
    {
      "rel": "parent",
      "href": "../collection.json",
      "type": "application/json"
    }
  ],
  "assets": {
    "dataformat": {
      "href": "20180426_201954_1p0a_LNO_1_DP_190",
      "type": "application/x-hdf5"
    }
  },
  "collection": "diffraction-order-190"
}
