{
  "type": "Feature",
  "stac_version": "1.1.0",
  "stac_extensions": [
    "https://stac-extensions.github.io/ssys/v1.1.0/schema.json"
  ],
  "id": "20180426_024853_1p0a_LNO_1_DF_134_00533_102",
  "geometry": {
    "type": "Polygon",
    "coordinates": [
      [
        [
          48.0968,
          -13.5929
        ],
        [
          48.3389,
          -13.4629
        ],
        [
          48.2654,
          -13.1394
        ],
        [
          48.2617,
          -13.1328
        ],
        [
          48.0191,
          -13.2615
        ],
        [
          48.0931,
          -13.5864
        ],
        [
          48.0968,
          -13.5929
        ]
      ]
    ]
  },
  "bbox": [
    48.0191,
    -13.5929,
    48.3389,
    -13.1328
  ],
  "properties": {
    "incidence_angle": 30.363,
    "emergence_angle": 0.582,
    "phase_angle": 30.264,
    "centre_latitude": -13.396,
    "centre_longitude": 48.167,
    "channel_temperature": -2.799,
    "start_datetime": "2018-04-26T03:24:32.941000Z",
    "end_datetime": "2018-04-26T03:24:39.567000Z",
    "platform": "exomars-trace-gas-orbiter",
    "instruments": [
      "NOMAD"
    ],
    "constellation": "exomars",
    "ssys:local_time": "34:165.420845:10.459",
    "mission": "ExoMars",
    "datetime": "2018-04-26T03:24:32.941000Z"
  },
  "links": [
    {
      "rel": "root",
      "href": "../../../catalog.json",
      "type": "application/json"
    },
    {
      "rel": "collection",
      "href": "../collection.json",
      "type": "application/json"
    },
    {
      "rel": "parent",
      "href": "../collection.json",
      "type": "application/json"
    }
  ],
  "assets": {
    "dataformat": {
      "href": "20180426_024853_1p0a_LNO_1_DF_134",
      "type": "application/x-hdf5"
    }
  },
  "collection": "diffraction-order-134"
}
