{
  "type": "Feature",
  "stac_version": "1.1.0",
  "stac_extensions": [
    "https://stac-extensions.github.io/ssys/v1.1.0/schema.json"
  ],
  "id": "20180425_070008_1p0a_LNO_1_DF_131_00533_151",
  "geometry": {
    "type": "Polygon",
    "coordinates": [
      [
        [
          -21.0558,
          -19.2022
        ],
        [
          -20.8249,
          -19.0383
        ],
        [
          -20.8762,
          -18.832
        ],
        [
          -20.8809,
          -18.8259
        ],
        [
          -21.1123,
          -18.9889
        ],
        [
          -21.0606,
          -19.1961
        ],
        [
          -21.0558,
          -19.2022
        ]
      ]
    ]
  },
  "bbox": [
    -21.1123,
    -19.2022,
    -20.8249,
    -18.8259
  ],
  "properties": {
    "incidence_angle": 32.059,
    "emergence_angle": 0.658,
    "phase_angle": 31.405,
    "centre_latitude": -19.041,
    "centre_longitude": -20.981,
    "channel_temperature": -4.903,
    "start_datetime": "2018-04-25T07:48:07.694000Z",
    "end_datetime": "2018-04-25T07:48:11.934000Z",
    "platform": "exomars-trace-gas-orbiter",
    "instruments": [
      "NOMAD"
    ],
    "constellation": "exomars",
    "ssys:local_time": "34:164.981282:10.764",
    "mission": "ExoMars",
    "datetime": "2018-04-25T07:48:07.694000Z"
  },
  "links": [
    {
      "rel": "root",
      "href": "../../../catalog.json",
      "type": "application/json"
    },
    {
      "rel": "collection",
      "href": "../collection.json",
      "type": "application/json"
    },
    {
      "rel": "parent",
      "href": "../collection.json",
      "type": "application/json"
    }
  ],
  "assets": {
    "dataformat": {
      "href": "20180425_070008_1p0a_LNO_1_DF_131",
      "type": "application/x-hdf5"
    }
  },
  "collection": "diffraction-order-131"
}
