{
  "type": "Feature",
  "stac_version": "1.1.0",
  "stac_extensions": [
    "https://stac-extensions.github.io/ssys/v1.1.0/schema.json"
  ],
  "id": "20180421_183121_1p0a_LNO_1_DF_134_00533_118",
  "geometry": {
    "type": "Polygon",
    "coordinates": [
      [
        [
          137.7221,
          9.1766
        ],
        [
          138.0033,
          9.2222
        ],
        [
          138.002,
          9.2299
        ],
        [
          137.9827,
          9.3184
        ],
        [
          137.7013,
          9.2733
        ],
        [
          137.7026,
          9.2656
        ],
        [
          137.7221,
          9.1766
        ]
      ]
    ]
  },
  "bbox": [
    137.7013,
    9.1766,
    138.0033,
    9.3184
  ],
  "properties": {
    "incidence_angle": 15.145,
    "emergence_angle": 0.261,
    "phase_angle": 15.105,
    "centre_latitude": 9.238,
    "centre_longitude": 137.834,
    "channel_temperature": -13.213,
    "start_datetime": "2018-04-21T19:11:03.375000Z",
    "end_datetime": "2018-04-21T19:11:05.198000Z",
    "platform": "exomars-trace-gas-orbiter",
    "instruments": [
      "NOMAD"
    ],
    "constellation": "exomars",
    "ssys:local_time": "34:163.091422:10.991",
    "ssys:targets": [
      "mars"
    ],
    "ssys:target_class": "planet",
    "mission": "ExoMars",
    "datetime": "2018-04-21T19:11:03.375000Z"
  },
  "links": [
    {
      "rel": "root",
      "href": "../../../catalog.json",
      "type": "application/json"
    },
    {
      "rel": "collection",
      "href": "../collection.json",
      "type": "application/json"
    },
    {
      "rel": "parent",
      "href": "../collection.json",
      "type": "application/json"
    }
  ],
  "assets": {
    "dataformat": {
      "href": "20180421_183121_1p0a_LNO_1_DF_134",
      "type": "application/x-hdf5"
    }
  },
  "collection": "diffraction-order-134"
}
