{
  "type": "Feature",
  "stac_version": "1.1.0",
  "stac_extensions": [
    "https://stac-extensions.github.io/ssys/v1.1.0/schema.json"
  ],
  "id": "20180421_203916_1p0a_LNO_1_DP_189_00533_179",
  "geometry": {
    "type": "Polygon",
    "coordinates": [
      [
        [
          141.2574,
          -63.4116
        ],
        [
          141.2725,
          -63.4086
        ],
        [
          141.0311,
          -63.1651
        ],
        [
          140.9086,
          -63.0918
        ],
        [
          140.8936,
          -63.0948
        ],
        [
          141.1332,
          -63.3385
        ],
        [
          141.2574,
          -63.4116
        ]
      ]
    ]
  },
  "bbox": [
    140.8936,
    -63.4116,
    141.2725,
    -63.0918
  ],
  "properties": {
    "incidence_angle": 72.696,
    "emergence_angle": 0.692,
    "phase_angle": 72.559,
    "centre_latitude": -63.275,
    "centre_longitude": 141.108,
    "channel_temperature": -8.132,
    "start_datetime": "2018-04-21T21:34:20.585000Z",
    "end_datetime": "2018-04-21T21:34:22.407000Z",
    "platform": "exomars-trace-gas-orbiter",
    "instruments": [
      "NOMAD"
    ],
    "constellation": "exomars",
    "ssys:local_time": "34:163.1446:13.53",
    "mission": "ExoMars",
    "datetime": "2018-04-21T21:34:20.585000Z"
  },
  "links": [
    {
      "rel": "root",
      "href": "../../../catalog.json",
      "type": "application/json"
    },
    {
      "rel": "collection",
      "href": "../collection.json",
      "type": "application/json"
    },
    {
      "rel": "parent",
      "href": "../collection.json",
      "type": "application/json"
    }
  ],
  "assets": {
    "dataformat": {
      "href": "20180421_203916_1p0a_LNO_1_DP_189",
      "type": "application/x-hdf5"
    }
  },
  "collection": "diffraction-order-189"
}
