{
  "type": "Feature",
  "stac_version": "1.1.0",
  "stac_extensions": [
    "https://stac-extensions.github.io/ssys/v1.1.0/schema.json"
  ],
  "id": "20180429_091417_1p0a_LNO_1_DP_190_00533_212",
  "geometry": {
    "type": "Polygon",
    "coordinates": [
      [
        [
          3.527,
          -66.4294
        ],
        [
          3.5455,
          -66.4289
        ],
        [
          3.4977,
          -66.1615
        ],
        [
          3.342,
          -66.0947
        ],
        [
          3.3236,
          -66.0952
        ],
        [
          3.3692,
          -66.3626
        ],
        [
          3.527,
          -66.4294
        ]
      ]
    ]
  },
  "bbox": [
    3.3236,
    -66.4294,
    3.5455,
    -66.0947
  ],
  "properties": {
    "incidence_angle": 72.739,
    "emergence_angle": 2.035,
    "phase_angle": 71.812,
    "centre_latitude": -66.286,
    "centre_longitude": 3.447,
    "channel_temperature": -4.23,
    "start_datetime": "2018-04-29T10:17:36.504000Z",
    "end_datetime": "2018-04-29T10:17:38.327000Z",
    "platform": "exomars-trace-gas-orbiter",
    "instruments": [
      "NOMAD"
    ],
    "constellation": "exomars",
    "ssys:local_time": "34:167.195596:12.255",
    "ssys:targets": [
      "mars"
    ],
    "ssys:target_class": "planet",
    "mission": "ExoMars",
    "datetime": "2018-04-29T10:17:36.504000Z"
  },
  "links": [
    {
      "rel": "root",
      "href": "../../../catalog.json",
      "type": "application/json"
    },
    {
      "rel": "collection",
      "href": "../collection.json",
      "type": "application/json"
    },
    {
      "rel": "parent",
      "href": "../collection.json",
      "type": "application/json"
    }
  ],
  "assets": {
    "dataformat": {
      "href": "20180429_091417_1p0a_LNO_1_DP_190",
      "type": "application/x-hdf5"
    }
  },
  "collection": "diffraction-order-190"
}
